.gitignore
LICENSE
README.md
setup.py
bin/pyreindent.py
pylineblocks/__init__.py
pylineblocks/pylineblocks.py
pylineblocks/tests/testPyblocks.py
pylineblocks/tests/testReindentIn.py
pylineblocks/tests/testReindentOut.py
pyreindent.egg-info/PKG-INFO
pyreindent.egg-info/SOURCES.txt
pyreindent.egg-info/dependency_links.txt
pyreindent.egg-info/top_level.txt