Metadata-Version: 1.1
Name: pyreindent
Version: 0.1
Summary: Freely switch between various Python indentation styles
Home-page: https://github.com/abernatskiy/pyreindent
Author: Anton Bernatskiy
Author-email: abernats@uvm.edu
License: MIT
Platform: UNKNOWN
Classifier: Development Status :: 4 - Beta
Classifier: License :: OSI Approved :: MIT License
Classifier: Programming Language :: Python :: 3
Classifier: Topic :: Text Processing :: Filters
